LICENSE.txt
MANIFEST.in
README.md
setup.cfg
setup.py
testhelpers/__init__.py
testhelpers/generator.py
testhelpers.egg-info/PKG-INFO
testhelpers.egg-info/SOURCES.txt
testhelpers.egg-info/dependency_links.txt
testhelpers.egg-info/top_level.txt
testhelpers.egg-info/zip-safe
testhelpers/tests/__init__.py
testhelpers/tests/test_generator.py