Metadata-Version: 1.0
Name: testhelpers
Version: 1.0.0
Summary: Python library to help with creating tests
Home-page: https://github.com/wtsi-hgi/python-test-helpers
Author: Colin Nolan
Author-email: colin.nolan@sanger.ac.uk
License: MIT
Platform: UNKNOWN
